iitornip/__init__.py
iitornip/__main__.py
iitornip/fetch_nodes.py
iitornip/iitornipd.py
iitornip/iitornipu.py
iitornip-1.0.0.dist-info/LICENSE
iitornip-1.0.0.dist-info/METADATA
iitornip-1.0.0.dist-info/WHEEL
iitornip-1.0.0.dist-info/entry_points.txt
iitornip-1.0.0.dist-info/top_level.txt
iitornip-1.0.0.dist-info/RECORD
